wideprint/__about__.py
wideprint/__init__.py
wideprint-0.1.1.dist-info/METADATA
wideprint-0.1.1.dist-info/WHEEL
wideprint-0.1.1.dist-info/RECORD
