Metadata-Version: 2.1
Name: wideprint
Version: 0.1.1
Summary: Print a collection of short strings into columns
Project-URL: Documentation, https://github.com/thehappycheese/wideprint#readme
Project-URL: Issues, https://github.com/thehappycheese/wideprint/issues
Project-URL: Source, https://github.com/thehappycheese/wideprint
Author: thehappycheese
License-Expression: MIT
Keywords: columns,print,terminal
Classifier: Development Status :: 5 - Production/Stable
Classifier: Programming Language :: Python :: 3.8
Classifier: Programming Language :: Python :: 3.9
Classifier: Programming Language :: Python :: 3.10
Requires-Python: >=3.7
